wolsocketproxy/__init__.py
wolsocketproxy/__main__.py
wolsocketproxy/monitor.py
wolsocketproxy/proxy.py
wolsocketproxy-0.1.1.dist-info/LICENSE
wolsocketproxy-0.1.1.dist-info/METADATA
wolsocketproxy-0.1.1.dist-info/WHEEL
wolsocketproxy-0.1.1.dist-info/entry_points.txt
wolsocketproxy-0.1.1.dist-info/RECORD
