Metadata-Version: 2.1
Name: wolsocketproxy
Version: 0.1.1
Summary: A socket proxy with wake-on-lan feature.
License: Apache-2.0
Author: Song Fuchang
Author-email: song.fc@gmail.com
Requires-Python: >=3.11,<4.0
Classifier: Development Status :: 5 - Production/Stable
Classifier: Intended Audience :: Developers
Classifier: Intended Audience :: System Administrators
Classifier: License :: OSI Approved :: Apache Software License
Classifier: Programming Language :: Python :: 3
Classifier: Programming Language :: Python :: 3.11
Classifier: Programming Language :: Python :: 3.12
Classifier: Programming Language :: Python :: 3.13
Classifier: Topic :: System :: Networking
Requires-Dist: dataclass-wizard (==0.28.0)
Requires-Dist: icmplib (==3.0.4)
Requires-Dist: wakeonlan (==3.1.0)
Project-URL: Changelog, https://github.com/notsyncing/wol-socket-proxy/releases
Project-URL: Issues, https://github.com/notsyncing/wol-socket-proxy/issues
